Workbook

Sheet Ventas
A1: Ferretería Don José — Registro de Ventas Mensuales 2024
A2: Datos de demostración — generados automáticamente con Python
A4: Mes | B4: Producto | C4: Categoría | D4: Unidades vendidas | E4: Precio unit. ($) | F4: Ingreso ($) | G4: Costo ($) | H4: Ganancia ($)
A5: Enero | B5: Tornillos 6x1 (caja x100) | C5: Fijaciones | D5: 936 | E5: 1.2 | F5: =D5*E5 | G5: =D5*0.45 | H5: =F5-G5
A6: Enero | B6: Pintura látex blanca 4L | C6: Pinturas | D6: 236 | E6: 18.5 | F6: =D6*E6 | G6: =D6*9.8 | H6: =F6-G6
A7: Enero | B7: Llave combinada 13mm | C7: Herramientas | D7: 130 | E7: 12 | F7: =D7*E7 | G7: =D7*5.5 | H7: =F7-G7
A8: Enero | B8: Cinta métrica 5m | C8: Medición | D8: 192 | E8: 8.9 | F8: =D8*E8 | G8: =D8*3.2 | H8: =F8-G8
A9: Enero | B9: Taladro percutor 650W | C9: Eléctricos | D9: 48 | E9: 89 | F9: =D9*E9 | G9: =D9*52.0 | H9: =F9-G9
A10: Enero | B10: Tubo PVC 110mm x 6m | C10: Plomería | D10: 201 | E10: 22 | F10: =D10*E10 | G10: =D10*11.5 | H10: =F10-G10
A11: Enero | B11: Lija al agua grano 120 | C11: Abrasivos | D11: 669 | E11: 1.8 | F11: =D11*E11 | G11: =D11*0.6 | H11: =F11-G11
A12: Enero | B12: Cerradura doble paleta | C12: Seguridad | D12: 78 | E12: 35 | F12: =D12*E12 | G12: =D12*17.0 | H12: =F12-G12
A13: Febrero | B13: Tornillos 6x1 (caja x100) | C13: Fijaciones | D13: 834 | E13: 1.2 | F13: =D13*E13 | G13: =D13*0.45 | H13: =F13-G13
A14: Febrero | B14: Pintura látex blanca 4L | C14: Pinturas | D14: 237 | E14: 18.5 | F14: =D14*E14 | G14: =D14*9.8 | H14: =F14-G14
A15: Febrero | B15: Llave combinada 13mm | C15: Herramientas | D15: 126 | E15: 12 | F15: =D15*E15 | G15: =D15*5.5 | H15: =F15-G15
A16: Febrero | B16: Cinta métrica 5m | C16: Medición | D16: 226 | E16: 8.9 | F16: =D16*E16 | G16: =D16*3.2 | H16: =F16-G16
A17: Febrero | B17: Taladro percutor 650W | C17: Eléctricos | D17: 32 | E17: 89 | F17: =D17*E17 | G17: =D17*52.0 | H17: =F17-G17
A18: Febrero | B18: Tubo PVC 110mm x 6m | C18: Plomería | D18: 154 | E18: 22 | F18: =D18*E18 | G18: =D18*11.5 | H18: =F18-G18
A19: Febrero | B19: Lija al agua grano 120 | C19: Abrasivos | D19: 598 | E19: 1.8 | F19: =D19*E19 | G19: =D19*0.6 | H19: =F19-G19
A20: Febrero | B20: Cerradura doble paleta | C20: Seguridad | D20: 102 | E20: 35 | F20: =D20*E20 | G20: =D20*17.0 | H20: =F20-G20
A21: Marzo | B21: Tornillos 6x1 (caja x100) | C21: Fijaciones | D21: 740 | E21: 1.2 | F21: =D21*E21 | G21: =D21*0.45 | H21: =F21-G21
A22: Marzo | B22: Pintura látex blanca 4L | C22: Pinturas | D22: 332 | E22: 18.5 | F22: =D22*E22 | G22: =D22*9.8 | H22: =F22-G22
A23: Marzo | B23: Llave combinada 13mm | C23: Herramientas | D23: 173 | E23: 12 | F23: =D23*E23 | G23: =D23*5.5 | H23: =F23-G23
A24: Marzo | B24: Cinta métrica 5m | C24: Medición | D24: 165 | E24: 8.9 | F24: =D24*E24 | G24: =D24*3.2 | H24: =F24-G24
A25: Marzo | B25: Taladro percutor 650W | C25: Eléctricos | D25: 50 | E25: 89 | F25: =D25*E25 | G25: =D25*52.0 | H25: =F25-G25
A26: Marzo | B26: Tubo PVC 110mm x 6m | C26: Plomería | D26: 204 | E26: 22 | F26: =D26*E26 | G26: =D26*11.5 | H26: =F26-G26
A27: Marzo | B27: Lija al agua grano 120 | C27: Abrasivos | D27: 506 | E27: 1.8 | F27: =D27*E27 | G27: =D27*0.6 | H27: =F27-G27
A28: Marzo | B28: Cerradura doble paleta | C28: Seguridad | D28: 81 | E28: 35 | F28: =D28*E28 | G28: =D28*17.0 | H28: =F28-G28
A29: Abril | B29: Tornillos 6x1 (caja x100) | C29: Fijaciones | D29: 1084 | E29: 1.2 | F29: =D29*E29 | G29: =D29*0.45 | H29: =F29-G29
A30: Abril | B30: Pintura látex blanca 4L | C30: Pinturas | D30: 289 | E30: 18.5 | F30: =D30*E30 | G30: =D30*9.8 | H30: =F30-G30
A31: Abril | B31: Llave combinada 13mm | C31: Herramientas | D31: 116 | E31: 12 | F31: =D31*E31 | G31: =D31*5.5 | H31: =F31-G31
A32: Abril | B32: Cinta métrica 5m | C32: Medición | D32: 176 | E32: 8.9 | F32: =D32*E32 | G32: =D32*3.2 | H32: =F32-G32
A33: Abril | B33: Taladro percutor 650W | C33: Eléctricos | D33: 51 | E33: 89 | F33: =D33*E33 | G33: =D33*52.0 | H33: =F33-G33
A34: Abril | B34: Tubo PVC 110mm x 6m | C34: Plomería | D34: 194 | E34: 22 | F34: =D34*E34 | G34: =D34*11.5 | H34: =F34-G34
A35: Abril | B35: Lija al agua grano 120 | C35: Abrasivos | D35: 644 | E35: 1.8 | F35: =D35*E35 | G35: =D35*0.6 | H35: =F35-G35
A36: Abril | B36: Cerradura doble paleta | C36: Seguridad | D36: 112 | E36: 35 | F36: =D36*E36 | G36: =D36*17.0 | H36: =F36-G36
A37: Mayo | B37: Tornillos 6x1 (caja x100) | C37: Fijaciones | D37: 888 | E37: 1.2 | F37: =D37*E37 | G37: =D37*0.45 | H37: =F37-G37
A38: Mayo | B38: Pintura látex blanca 4L | C38: Pinturas | D38: 398 | E38: 18.5 | F38: =D38*E38 | G38: =D38*9.8 | H38: =F38-G38
A39: Mayo | B39: Llave combinada 13mm | C39: Herramientas | D39: 138 | E39: 12 | F39: =D39*E39 | G39: =D39*5.5 | H39: =F39-G39
A40: Mayo | B40: Cinta métrica 5m | C40: Medición | D40: 231 | E40: 8.9 | F40: =D40*E40 | G40: =D40*3.2 | H40: =F40-G40
A41: Mayo | B41: Taladro percutor 650W | C41: Eléctricos | D41: 50 | E41: 89 | F41: =D41*E41 | G41: =D41*52.0 | H41: =F41-G41
A42: Mayo | B42: Tubo PVC 110mm x 6m | C42: Plomería | D42: 196 | E42: 22 | F42: =D42*E42 | G42: =D42*11.5 | H42: =F42-G42
A43: Mayo | B43: Lija al agua grano 120 | C43: Abrasivos | D43: 660 | E43: 1.8 | F43: =D43*E43 | G43: =D43*0.6 | H43: =F43-G43
A44: Mayo | B44: Cerradura doble paleta | C44: Seguridad | D44: 104 | E44: 35 | F44: =D44*E44 | G44: =D44*17.0 | H44: =F44-G44
A45: Junio | B45: Tornillos 6x1 (caja x100) | C45: Fijaciones | D45: 1160 | E45: 1.2 | F45: =D45*E45 | G45: =D45*0.45 | H45: =F45-G45
A46: Junio | B46: Pintura látex blanca 4L | C46: Pinturas | D46: 288 | E46: 18.5 | F46: =D46*E46 | G46: =D46*9.8 | H46: =F46-G46
A47: Junio | B47: Llave combinada 13mm | C47: Herramientas | D47: 152 | E47: 12 | F47: =D47*E47 | G47: =D47*5.5 | H47: =F47-G47
A48: Junio | B48: Cinta métrica 5m | C48: Medición | D48: 240 | E48: 8.9 | F48: =D48*E48 | G48: =D48*3.2 | H48: =F48-G48
A49: Junio | B49: Taladro percutor 650W | C49: Eléctricos | D49: 40 | E49: 89 | F49: =D49*E49 | G49: =D49*52.0 | H49: =F49-G49
A50: Junio | B50: Tubo PVC 110mm x 6m | C50: Plomería | D50: 189 | E50: 22 | F50: =D50*E50 | G50: =D50*11.5 | H50: =F50-G50
A51: Junio | B51: Lija al agua grano 120 | C51: Abrasivos | D51: 521 | E51: 1.8 | F51: =D51*E51 | G51: =D51*0.6 | H51: =F51-G51
A52: Junio | B52: Cerradura doble paleta | C52: Seguridad | D52: 106 | E52: 35 | F52: =D52*E52 | G52: =D52*17.0 | H52: =F52-G52
A53: Julio | B53: Tornillos 6x1 (caja x100) | C53: Fijaciones | D53: 1121 | E53: 1.2 | F53: =D53*E53 | G53: =D53*0.45 | H53: =F53-G53
A54: Julio | B54: Pintura látex blanca 4L | C54: Pinturas | D54: 353 | E54: 18.5 | F54: =D54*E54 | G54: =D54*9.8 | H54: =F54-G54
A55: Julio | B55: Llave combinada 13mm | C55: Herramientas | D55: 165 | E55: 12 | F55: =D55*E55 | G55: =D55*5.5 | H55: =F55-G55
A56: Julio | B56: Cinta métrica 5m | C56: Medición | D56: 228 | E56: 8.9 | F56: =D56*E56 | G56: =D56*3.2 | H56: =F56-G56
A57: Julio | B57: Taladro percutor 650W | C57: Eléctricos | D57: 45 | E57: 89 | F57: =D57*E57 | G57: =D57*52.0 | H57: =F57-G57
A58: Julio | B58: Tubo PVC 110mm x 6m | C58: Plomería | D58: 273 | E58: 22 | F58: =D58*E58 | G58: =D58*11.5 | H58: =F58-G58
A59: Julio | B59: Lija al agua grano 120 | C59: Abrasivos | D59: 716 | E59: 1.8 | F59: =D59*E59 | G59: =D59*0.6 | H59: =F59-G59
A60: Julio | B60: Cerradura doble paleta | C60: Seguridad | D60: 127 | E60: 35 | F60: =D60*E60 | G60: =D60*17.0 | H60: =F60-G60
A61: Agosto | B61: Tornillos 6x1 (caja x100) | C61: Fijaciones | D61: 717 | E61: 1.2 | F61: =D61*E61 | G61: =D61*0.45 | H61: =F61-G61
A62: Agosto | B62: Pintura látex blanca 4L | C62: Pinturas | D62: 356 | E62: 18.5 | F62: =D62*E62 | G62: =D62*9.8 | H62: =F62-G62
A63: Agosto | B63: Llave combinada 13mm | C63: Herramientas | D63: 121 | E63: 12 | F63: =D63*E63 | G63: =D63*5.5 | H63: =F63-G63
A64: Agosto | B64: Cinta métrica 5m | C64: Medición | D64: 210 | E64: 8.9 | F64: =D64*E64 | G64: =D64*3.2 | H64: =F64-G64
A65: Agosto | B65: Taladro percutor 650W | C65: Eléctricos | D65: 54 | E65: 89 | F65: =D65*E65 | G65: =D65*52.0 | H65: =F65-G65
A66: Agosto | B66: Tubo PVC 110mm x 6m | C66: Plomería | D66: 198 | E66: 22 | F66: =D66*E66 | G66: =D66*11.5 | H66: =F66-G66
A67: Agosto | B67: Lija al agua grano 120 | C67: Abrasivos | D67: 570 | E67: 1.8 | F67: =D67*E67 | G67: =D67*0.6 | H67: =F67-G67
A68: Agosto | B68: Cerradura doble paleta | C68: Seguridad | D68: 110 | E68: 35 | F68: =D68*E68 | G68: =D68*17.0 | H68: =F68-G68
A69: Septiembre | B69: Tornillos 6x1 (caja x100) | C69: Fijaciones | D69: 1031 | E69: 1.2 | F69: =D69*E69 | G69: =D69*0.45 | H69: =F69-G69
A70: Septiembre | B70: Pintura látex blanca 4L | C70: Pinturas | D70: 364 | E70: 18.5 | F70: =D70*E70 | G70: =D70*9.8 | H70: =F70-G70
A71: Septiembre | B71: Llave combinada 13mm | C71: Herramientas | D71: 127 | E71: 12 | F71: =D71*E71 | G71: =D71*5.5 | H71: =F71-G71
A72: Septiembre | B72: Cinta métrica 5m | C72: Medición | D72: 168 | E72: 8.9 | F72: =D72*E72 | G72: =D72*3.2 | H72: =F72-G72
A73: Septiembre | B73: Taladro percutor 650W | C73: Eléctricos | D73: 38 | E73: 89 | F73: =D73*E73 | G73: =D73*52.0 | H73: =F73-G73
A74: Septiembre | B74: Tubo PVC 110mm x 6m | C74: Plomería | D74: 161 | E74: 22 | F74: =D74*E74 | G74: =D74*11.5 | H74: =F74-G74
A75: Septiembre | B75: Lija al agua grano 120 | C75: Abrasivos | D75: 467 | E75: 1.8 | F75: =D75*E75 | G75: =D75*0.6 | H75: =F75-G75
A76: Septiembre | B76: Cerradura doble paleta | C76: Seguridad | D76: 124 | E76: 35 | F76: =D76*E76 | G76: =D76*17.0 | H76: =F76-G76
A77: Octubre | B77: Tornillos 6x1 (caja x100) | C77: Fijaciones | D77: 1047 | E77: 1.2 | F77: =D77*E77 | G77: =D77*0.45 | H77: =F77-G77
A78: Octubre | B78: Pintura látex blanca 4L | C78: Pinturas | D78: 286 | E78: 18.5 | F78: =D78*E78 | G78: =D78*9.8 | H78: =F78-G78
A79: Octubre | B79: Llave combinada 13mm | C79: Herramientas | D79: 161 | E79: 12 | F79: =D79*E79 | G79: =D79*5.5 | H79: =F79-G79
A80: Octubre | B80: Cinta métrica 5m | C80: Medición | D80: 212 | E80: 8.9 | F80: =D80*E80 | G80: =D80*3.2 | H80: =F80-G80
A81: Octubre | B81: Taladro percutor 650W | C81: Eléctricos | D81: 52 | E81: 89 | F81: =D81*E81 | G81: =D81*52.0 | H81: =F81-G81
A82: Octubre | B82: Tubo PVC 110mm x 6m | C82: Plomería | D82: 180 | E82: 22 | F82: =D82*E82 | G82: =D82*11.5 | H82: =F82-G82
A83: Octubre | B83: Lija al agua grano 120 | C83: Abrasivos | D83: 483 | E83: 1.8 | F83: =D83*E83 | G83: =D83*0.6 | H83: =F83-G83
A84: Octubre | B84: Cerradura doble paleta | C84: Seguridad | D84: 86 | E84: 35 | F84: =D84*E84 | G84: =D84*17.0 | H84: =F84-G84
A85: Noviembre | B85: Tornillos 6x1 (caja x100) | C85: Fijaciones | D85: 1034 | E85: 1.2 | F85: =D85*E85 | G85: =D85*0.45 | H85: =F85-G85
A86: Noviembre | B86: Pintura látex blanca 4L | C86: Pinturas | D86: 318 | E86: 18.5 | F86: =D86*E86 | G86: =D86*9.8 | H86: =F86-G86
A87: Noviembre | B87: Llave combinada 13mm | C87: Herramientas | D87: 178 | E87: 12 | F87: =D87*E87 | G87: =D87*5.5 | H87: =F87-G87
A88: Noviembre | B88: Cinta métrica 5m | C88: Medición | D88: 314 | E88: 8.9 | F88: =D88*E88 | G88: =D88*3.2 | H88: =F88-G88
A89: Noviembre | B89: Taladro percutor 650W | C89: Eléctricos | D89: 46 | E89: 89 | F89: =D89*E89 | G89: =D89*52.0 | H89: =F89-G89
A90: Noviembre | B90: Tubo PVC 110mm x 6m | C90: Plomería | D90: 180 | E90: 22 | F90: =D90*E90 | G90: =D90*11.5 | H90: =F90-G90
A91: Noviembre | B91: Lija al agua grano 120 | C91: Abrasivos | D91: 806 | E91: 1.8 | F91: =D91*E91 | G91: =D91*0.6 | H91: =F91-G91
A92: Noviembre | B92: Cerradura doble paleta | C92: Seguridad | D92: 116 | E92: 35 | F92: =D92*E92 | G92: =D92*17.0 | H92: =F92-G92
A93: Diciembre | B93: Tornillos 6x1 (caja x100) | C93: Fijaciones | D93: 782 | E93: 1.2 | F93: =D93*E93 | G93: =D93*0.45 | H93: =F93-G93
A94: Diciembre | B94: Pintura látex blanca 4L | C94: Pinturas | D94: 276 | E94: 18.5 | F94: =D94*E94 | G94: =D94*9.8 | H94: =F94-G94
A95: Diciembre | B95: Llave combinada 13mm | C95: Herramientas | D95: 135 | E95: 12 | F95: =D95*E95 | G95: =D95*5.5 | H95: =F95-G95
A96: Diciembre | B96: Cinta métrica 5m | C96: Medición | D96: 277 | E96: 8.9 | F96: =D96*E96 | G96: =D96*3.2 | H96: =F96-G96
A97: Diciembre | B97: Taladro percutor 650W | C97: Eléctricos | D97: 57 | E97: 89 | F97: =D97*E97 | G97: =D97*52.0 | H97: =F97-G97
A98: Diciembre | B98: Tubo PVC 110mm x 6m | C98: Plomería | D98: 203 | E98: 22 | F98: =D98*E98 | G98: =D98*11.5 | H98: =F98-G98
A99: Diciembre | B99: Lija al agua grano 120 | C99: Abrasivos | D99: 487 | E99: 1.8 | F99: =D99*E99 | G99: =D99*0.6 | H99: =F99-G99
A100: Diciembre | B100: Cerradura doble paleta | C100: Seguridad | D100: 108 | E100: 35 | F100: =D100*E100 | G100: =D100*17.0 | H100: =F100-G100
B101: TOTAL GENERAL | D101: =SUM(D5:D100) | F101: =SUM(F5:F100) | G101: =SUM(G5:G100) | H101: =SUM(H5:H100)

Sheet Resumen mensual
A1: Resumen de ingresos y ganancias por mes
A3: Mes | B3: Ingresos ($) | C3: Costos ($) | D3: Ganancia ($)
A4: Enero | B4: =SUMIF(Ventas!A:A,A4,Ventas!F:F) | C4: =SUMIF(Ventas!A:A,A4,Ventas!G:G) | D4: =B4-C4
A5: Febrero | B5: =SUMIF(Ventas!A:A,A5,Ventas!F:F) | C5: =SUMIF(Ventas!A:A,A5,Ventas!G:G) | D5: =B5-C5
A6: Marzo | B6: =SUMIF(Ventas!A:A,A6,Ventas!F:F) | C6: =SUMIF(Ventas!A:A,A6,Ventas!G:G) | D6: =B6-C6
A7: Abril | B7: =SUMIF(Ventas!A:A,A7,Ventas!F:F) | C7: =SUMIF(Ventas!A:A,A7,Ventas!G:G) | D7: =B7-C7
A8: Mayo | B8: =SUMIF(Ventas!A:A,A8,Ventas!F:F) | C8: =SUMIF(Ventas!A:A,A8,Ventas!G:G) | D8: =B8-C8
A9: Junio | B9: =SUMIF(Ventas!A:A,A9,Ventas!F:F) | C9: =SUMIF(Ventas!A:A,A9,Ventas!G:G) | D9: =B9-C9
A10: Julio | B10: =SUMIF(Ventas!A:A,A10,Ventas!F:F) | C10: =SUMIF(Ventas!A:A,A10,Ventas!G:G) | D10: =B10-C10
A11: Agosto | B11: =SUMIF(Ventas!A:A,A11,Ventas!F:F) | C11: =SUMIF(Ventas!A:A,A11,Ventas!G:G) | D11: =B11-C11
A12: Septiembre | B12: =SUMIF(Ventas!A:A,A12,Ventas!F:F) | C12: =SUMIF(Ventas!A:A,A12,Ventas!G:G) | D12: =B12-C12
A13: Octubre | B13: =SUMIF(Ventas!A:A,A13,Ventas!F:F) | C13: =SUMIF(Ventas!A:A,A13,Ventas!G:G) | D13: =B13-C13
A14: Noviembre | B14: =SUMIF(Ventas!A:A,A14,Ventas!F:F) | C14: =SUMIF(Ventas!A:A,A14,Ventas!G:G) | D14: =B14-C14
A15: Diciembre | B15: =SUMIF(Ventas!A:A,A15,Ventas!F:F) | C15: =SUMIF(Ventas!A:A,A15,Ventas!G:G) | D15: =B15-C15
